clickable_confusion_matrix/__init__.py
clickable_confusion_matrix/ccm.py
clickable_confusion_matrix-0.1.1.dist-info/LICENSE
clickable_confusion_matrix-0.1.1.dist-info/METADATA
clickable_confusion_matrix-0.1.1.dist-info/WHEEL
clickable_confusion_matrix-0.1.1.dist-info/top_level.txt
clickable_confusion_matrix-0.1.1.dist-info/RECORD
